b_aws_dynamodb_backup/__init__.py
b_aws_dynamodb_backup/color_print.py
b_aws_dynamodb_backup/print_colors.py
b_aws_dynamodb_backup/cli_actions/__init__.py
b_aws_dynamodb_backup/cli_actions/backup.py
b_aws_dynamodb_backup/cli_actions/base_cli_actions.py
b_aws_dynamodb_backup/cli_actions/restore.py
b_aws_dynamodb_backup/cli_actions/seed.py
b_aws_dynamodb_backup/db_actions/__init__.py
b_aws_dynamodb_backup/db_actions/base_db_action.py
b_aws_dynamodb_backup/db_actions/download_db.py
b_aws_dynamodb_backup/db_actions/seed_db.py
b_aws_dynamodb_backup/db_actions/upload_db.py
b_aws_dynamodb_backup/exceptions/__init__.py
b_aws_dynamodb_backup/exceptions/backup_not_found.py
b_aws_dynamodb_backup/exceptions/database_not_found.py
b_aws_dynamodb_backup/util/__init__.py
b_aws_dynamodb_backup/util/dynamodb_serializer.py
b_aws_dynamodb_backup-1.1.1.dist-info/LICENSE
b_aws_dynamodb_backup-1.1.1.dist-info/METADATA
b_aws_dynamodb_backup-1.1.1.dist-info/WHEEL
b_aws_dynamodb_backup-1.1.1.dist-info/entry_points.txt
b_aws_dynamodb_backup-1.1.1.dist-info/top_level.txt
b_aws_dynamodb_backup-1.1.1.dist-info/RECORD
