Metadata-Version: 2.1
Name: b-aws-dynamodb-backup
Version: 1.1.1
Summary: DynamoDB.
Home-page: https://github.com/biomapas/B.AwsDynamoDbBackup.git
Author: Laimonas Sutkus
Author-email: laimonas.sutkus@biomapas.com
License: Apache License 2.0
Keywords: DynamoDB
Platform: UNKNOWN
Requires-Dist: boto3
Requires-Dist: b-continuous-subprocess (<1.0.0,>=0.3.2)
